url_cleaner/__init__.py
url_cleaner/filter.py
url_cleaner/ruler.py
url_cleaner/rules.json
url_cleaner/rules_remote_general.txt
url_cleaner/rules_remote_specific.txt
url_cleaner/url.py
url_cleaner-0.1.5.dist-info/METADATA
url_cleaner-0.1.5.dist-info/WHEEL
url_cleaner-0.1.5.dist-info/licenses/LICENCE
url_cleaner-0.1.5.dist-info/RECORD
