Metadata-Version: 2.1
Name: url_cleaner
Version: 0.1.5
Summary: A package for removing tracing parameters from URLs. This package supports automatically updating filtering rules from Adguard
Project-URL: Homepage, https://github.com/fireindark707/url_cleaner
Project-URL: Bug Tracker, https://github.com/fireindark707/url_cleaner/issues
Author-email: phoenix000 <phoenix000.taipei@gmail.com>
License-File: LICENCE
Classifier: License :: OSI Approved :: MIT License
Classifier: Operating System :: OS Independent
Classifier: Programming Language :: Python :: 3
Requires-Python: >=3.6
